sharded_photos_drive_cli_client/__init__.py
sharded_photos_drive_cli_client/backup/backup_photos.py
sharded_photos_drive_cli_client/backup/diffs.py
sharded_photos_drive_cli_client/backup/diffs_assignments.py
sharded_photos_drive_cli_client/backup/gphotos_uploader.py
sharded_photos_drive_cli_client/backup/processed_diffs.py
sharded_photos_drive_cli_client/clean/clean_system.py
sharded_photos_drive_cli_client/cli/app.py
sharded_photos_drive_cli_client/cli/commands/add.py
sharded_photos_drive_cli_client/cli/commands/clean.py
sharded_photos_drive_cli_client/cli/commands/config/__init__.py
sharded_photos_drive_cli_client/cli/commands/config/add.py
sharded_photos_drive_cli_client/cli/commands/config/init.py
sharded_photos_drive_cli_client/cli/commands/config/reauthorize.py
sharded_photos_drive_cli_client/cli/commands/db/__init__.py
sharded_photos_drive_cli_client/cli/commands/db/delete_media_item_ids.py
sharded_photos_drive_cli_client/cli/commands/db/dump.py
sharded_photos_drive_cli_client/cli/commands/db/restore.py
sharded_photos_drive_cli_client/cli/commands/db/set_media_item_width_height_date_taken_fields.py
sharded_photos_drive_cli_client/cli/commands/delete.py
sharded_photos_drive_cli_client/cli/commands/sync.py
sharded_photos_drive_cli_client/cli/commands/teardown.py
sharded_photos_drive_cli_client/cli/commands/usage.py
sharded_photos_drive_cli_client/cli/shared/config.py
sharded_photos_drive_cli_client/cli/shared/files.py
sharded_photos_drive_cli_client/cli/shared/inputs.py
sharded_photos_drive_cli_client/cli/shared/logging.py
sharded_photos_drive_cli_client/cli/shared/printer.py
sharded_photos_drive_cli_client/cli/shared/typer.py
sharded_photos_drive_cli_client/diff/get_diffs.py
sharded_photos_drive_cli_client/py.typed
sharded_photos_drive_cli_client/shared/blob_store/gphotos/albums.py
sharded_photos_drive_cli_client/shared/blob_store/gphotos/albums_client.py
sharded_photos_drive_cli_client/shared/blob_store/gphotos/client.py
sharded_photos_drive_cli_client-4.0.0.dist-info/METADATA
sharded_photos_drive_cli_client-4.0.0.dist-info/WHEEL
sharded_photos_drive_cli_client-4.0.0.dist-info/entry_points.txt
sharded_photos_drive_cli_client-4.0.0.dist-info/RECORD
