Metadata-Version: 2.3
Name: sharded_photos_drive_cli_client
Version: 4.0.0
Summary: 
Author: Emilio Kartono
Author-email: e.kartonoe@gmail.com
Requires-Python: >=3.13,<4.0
Classifier: Programming Language :: Python :: 3
Classifier: Programming Language :: Python :: 3.13
Requires-Dist: backoff (>=2.2.1,<3.0.0)
Requires-Dist: dacite (>=1.8.1,<2.0.0)
Requires-Dist: event-bus (>=1.0.2,<2.0.0)
Requires-Dist: exifread (>=3.0.0,<4.0.0)
Requires-Dist: google-api-python-client (>=2.156.0,<3.0.0)
Requires-Dist: google-auth-oauthlib (>=1.2.1,<2.0.0)
Requires-Dist: opencv-python-headless (>=4.11.0.86,<5.0.0.0)
Requires-Dist: pillow (>=11.2.1,<12.0.0)
Requires-Dist: pillow-heif (>=0.22.0,<0.23.0)
Requires-Dist: prettytable (>=3.12.0,<4.0.0)
Requires-Dist: pyexiftool (>=0.5.6,<0.6.0)
Requires-Dist: pymongo (>=4.10.1,<5.0.0)
Requires-Dist: python-magic (>=0.4.27,<0.5.0)
Requires-Dist: termcolor (>=2.5.0,<3.0.0)
Requires-Dist: tqdm (>=4.67.1,<5.0.0)
Requires-Dist: typer (>=0.15.1,<0.16.0)
Requires-Dist: types-exifread (>=3.0.0.20240806,<4.0.0.0)
Requires-Dist: types-requests (>=2.32.0.20241016,<3.0.0.0)
Requires-Dist: xxhash (>=3.5.0,<4.0.0)
